pyebur128-0.1.1.dist-info/LICENSE
pyebur128-0.1.1.dist-info/zip-safe
pyebur128-0.1.1.dist-info/METADATA
pyebur128-0.1.1.dist-info/top_level.txt
pyebur128-0.1.1.dist-info/RECORD
pyebur128-0.1.1.dist-info/WHEEL
pyebur128/pyebur128.pyx
pyebur128/pyebur128.cpython-311-i386-linux-musl.so
pyebur128/pyebur128.c
pyebur128/__init__.py
pyebur128/pyebur128.pxd
pyebur128/version.py
